[
  {
    "outputFileName": "wwwroot/css/stylesheets.min.css",
    "inputFiles": [
      "Lib/external/twitter-bootstrap/css/bootstrap.min.css",
      "Lib/external/toastr.js/toastr.min.css",
      "Lib/local/css/site.css"
    ]
  },
  {
    "outputFileName": "wwwroot/js/scripts.min.js",
    "inputFiles": [
      "Lib/external/jquery/jquery.min.js",
      "Lib/external/twitter-bootstrap/js/bootstrap.bundle.min.js",
      "Lib/external/mithril/mithril.min.js",
      "Lib/external/moment.js/moment.min.js",
      "Lib/external/toastr.js/toastr.min.js",
      "Lib/external/fingerprintjs2/fingerprint2.min.js",
      "Lib/external/apexcharts/apexcharts.min.js",
      "Lib/local/js/site.js",
      "Lib/local/js/night-mode.js",
      "Lib/local/js/mithril/models/*.js",
      "Lib/local/js/mithril/views/*.js"
    ],
    "minify": {
      "enabled": true,
      "renameLocals": true
    },
    "sourceMap": false
  },
  {
    "outputFileName": "wwwroot/js/jquery-bootstrap.min.js",
    "inputFiles": [
      "Lib/external/jquery/jquery.min.js",
      "Lib/external/moment.js/moment.min.js",
      "Lib/external/twitter-bootstrap/js/bootstrap.bundle.min.js",
      "Lib/local/js/events.js",
      "Lib/local/js/night-mode.js"
    ]
  }
]